django_userforeignkey/__init__.py
django_userforeignkey/middleware.py
django_userforeignkey/request.py
django_userforeignkey/models/__init__.py
django_userforeignkey/models/fields.py
django_userforeignkey-0.5.0.dist-info/LICENSE
django_userforeignkey-0.5.0.dist-info/METADATA
django_userforeignkey-0.5.0.dist-info/WHEEL
django_userforeignkey-0.5.0.dist-info/top_level.txt
django_userforeignkey-0.5.0.dist-info/RECORD
